dimpy/__init__.py
dimpy/basis.py
dimpy/dimension_vector.py
dimpy/dimensioned_array.py
dimpy/exceptions.py
dimpy/ufuncs.py
multi_dimpy-0.2.4.dist-info/LICENSE
multi_dimpy-0.2.4.dist-info/METADATA
multi_dimpy-0.2.4.dist-info/WHEEL
multi_dimpy-0.2.4.dist-info/RECORD
