Metadata-Version: 2.3
Name: multi-dimpy
Version: 0.2.4
Summary: NumPy-wrapper for dimensioned arrays.
License: MIT
Keywords: array,dimension,dimensional,engineering,linear algebra,mathematics,matrices,matrix,NumPy,physics,quantities,science,scientific computing,units
Author: Nathan Schill
Author-email: nateschill@gmail.com
Requires-Python: >=3.10
Classifier: Development Status :: 1 - Planning
Classifier: Intended Audience :: Developers
Classifier: Intended Audience :: Science/Research
Classifier: License :: OSI Approved :: MIT License
Classifier: Programming Language :: Python :: 3.10
Classifier: Topic :: Scientific/Engineering
Classifier: Topic :: Software Development :: Build Tools
Requires-Dist: numpy (>=2.2.5,<3.0.0)
Project-URL: Bug Tracker, https://github.com/schilln/multi-dimpy/issues
Project-URL: Repository, https://github.com/schilln/multi-dimpy
